lithi/__init__.py
lithi/app.py
lithi/bizlog/__init__.py
lithi/bizlog/brand.py
lithi/bizlog/settings.py
lithi/commands/__init__.py
lithi/commands/config.py
lithi/commands/development.py
lithi/commands/memory.py
lithi/core/__init__.py
lithi/core/cli.py
lithi/core/config.py
lithi/core/core.py
lithi/core/logger.py
lithi/implementation/__init__.py
lithi/implementation/jlink.py
lithi/implementation/sim.py
lithi/interface/__init__.py
lithi/interface/target.py
lithi-0.1.4.dist-info/METADATA
lithi-0.1.4.dist-info/WHEEL
lithi-0.1.4.dist-info/entry_points.txt
lithi-0.1.4.dist-info/RECORD
