Metadata-Version: 2.4
Name: lithi
Version: 0.1.4
Summary: ELF parser and memory live inspector
Project-URL: Homepage, https://pypi.org/project/lithi/
Author-email: Kanelis Elias <e.kanelis@voidbuffer.com>
Maintainer-email: Kanelis Elias <e.kanelis@voidbuffer.com>
Keywords: elf,inspect,jlink,mcu,memory
Classifier: Development Status :: 3 - Alpha
Classifier: Programming Language :: Python :: 3
Classifier: Programming Language :: Python :: 3.10
Requires-Python: >=3.10
Requires-Dist: click>=8.3.0
Requires-Dist: colorama>=0.4.6
Requires-Dist: pydantic-settings>=2.11.0
Requires-Dist: pydantic>=2.12.3
Requires-Dist: pylink-square>=2.0.0
Requires-Dist: xdg-base-dirs>=6.0.2
